{"title":"Chrome 浏览器常用快捷键","uid":"212ace37ed6016bdbeaf8c136445f0e5","slug":"快捷键/Chrome 浏览器常用快捷键","date":"2019-08-24T00:30:00.000Z","updated":"2023-09-06T08:45:06.360Z","comments":true,"path":"api/articles/快捷键/Chrome 浏览器常用快捷键.json","keywords":null,"cover":"/images/cover/6.jpg","content":"<h1 id=\"Chrome-浏览器常用快捷键\"><a href=\"#Chrome-浏览器常用快捷键\" class=\"headerlink\" title=\"Chrome 浏览器常用快捷键\"></a>Chrome 浏览器常用快捷键</h1><h2 id=\"Mac-上的-Chrome-快捷键\"><a href=\"#Mac-上的-Chrome-快捷键\" class=\"headerlink\" title=\"Mac 上的 Chrome 快捷键\"></a>Mac 上的 Chrome 快捷键</h2><hr>\n<h3 id=\"导航\"><a href=\"#导航\" class=\"headerlink\" title=\"导航\"></a>导航</h3><ul>\n<li>打开新标签页：<code>Command + T</code></li>\n<li>关闭当前标签页：<code>Command + W</code></li>\n<li>切换到下一个标签页：<code>Control + Tab</code></li>\n<li>切换到上一个标签页：<code>Control + Shift + Tab</code></li>\n<li>切换到特定的标签页：<code>Command + 数字键</code>（例如，<code>Command + 1</code> 切换到第一个标签页）</li>\n<li>重新加载当前页面：<code>Command + R</code></li>\n<li>停止加载页面：<code>Command + .</code></li>\n</ul>\n<hr>\n<h3 id=\"标签页操作\"><a href=\"#标签页操作\" class=\"headerlink\" title=\"标签页操作\"></a>标签页操作</h3><ul>\n<li>在新标签页中打开链接：<code>Command + 点击链接</code></li>\n<li>在后台打开链接：<code>Command + 点击链接</code></li>\n<li>关闭当前窗口：<code>Command + Shift + W</code></li>\n<li>最小化窗口：<code>Command + M</code></li>\n<li>全屏模式切换：<code>Control + Command + F</code></li>\n</ul>\n<hr>\n<h3 id=\"查找和搜索\"><a href=\"#查找和搜索\" class=\"headerlink\" title=\"查找和搜索\"></a>查找和搜索</h3><ul>\n<li>在页面中查找：<code>Command + F</code></li>\n<li>查找下一个匹配项：<code>Command + G</code></li>\n<li>查找上一个匹配项：<code>Command + Shift + G</code></li>\n<li>在新标签页中进行搜索：<code>Command + L</code>，然后输入搜索关键词，按 <code>Enter</code> 键</li>\n</ul>\n<hr>\n<h3 id=\"开发者工具\"><a href=\"#开发者工具\" class=\"headerlink\" title=\"开发者工具\"></a>开发者工具</h3><ul>\n<li>打开开发者工具：<code>Option + Command + I</code></li>\n<li>打开开发者工具的控制台面板：<code>Option + Command + J</code></li>\n<li>切换到下一个面板：<code>Control + ]</code></li>\n<li>切换到上一个面板：<code>Control + [</code></li>\n</ul>\n<hr>\n<h3 id=\"其他操作\"><a href=\"#其他操作\" class=\"headerlink\" title=\"其他操作\"></a>其他操作</h3><ul>\n<li>打开历史记录：<code>Command + Y</code></li>\n<li>打开书签栏：<code>Command + Shift + B</code></li>\n<li>打开下载页面：<code>Command + Shift + J</code></li>\n</ul>\n<h2 id=\"Windows-上的-Chrome-快捷键\"><a href=\"#Windows-上的-Chrome-快捷键\" class=\"headerlink\" title=\"Windows 上的 Chrome 快捷键\"></a>Windows 上的 Chrome 快捷键</h2><hr>\n<h3 id=\"导航-1\"><a href=\"#导航-1\" class=\"headerlink\" title=\"导航\"></a>导航</h3><ul>\n<li>打开新标签页：<code>Ctrl + T</code></li>\n<li>关闭当前标签页：<code>Ctrl + W</code></li>\n<li>切换到下一个标签页：<code>Ctrl + Tab</code></li>\n<li>切换到上一个标签页：<code>Ctrl + Shift + Tab</code></li>\n<li>切换到特定的标签页：<code>Ctrl + 数字键</code>（例如，<code>Ctrl + 1</code> 切换到第一个标签页）</li>\n<li>重新加载当前页面：<code>Ctrl + R</code></li>\n<li>停止加载页面：<code>Esc</code></li>\n</ul>\n<hr>\n<h3 id=\"标签页操作-1\"><a href=\"#标签页操作-1\" class=\"headerlink\" title=\"标签页操作\"></a>标签页操作</h3><ul>\n<li>在新标签页中打开链接：<code>Ctrl + 点击链接</code></li>\n<li>在后台打开链接：<code>Ctrl + 点击链接</code></li>\n<li>关闭当前窗口：<code>Ctrl + Shift + W</code></li>\n<li>最小化窗口：<code>Alt + Space, N</code></li>\n<li>全屏模式切换：<code>F11</code></li>\n</ul>\n<hr>\n<h3 id=\"查找和搜索-1\"><a href=\"#查找和搜索-1\" class=\"headerlink\" title=\"查找和搜索\"></a>查找和搜索</h3><ul>\n<li>在页面中查找：<code>Ctrl + F</code></li>\n<li>查找下一个匹配项：<code>Ctrl + G</code></li>\n<li>查找上一个匹配项：<code>Ctrl + Shift + G</code></li>\n<li>在新标签页中进行搜索：<code>Ctrl + L</code>，然后输入搜索关键词，按 <code>Enter</code> 键</li>\n</ul>\n<hr>\n<h3 id=\"开发者工具-1\"><a href=\"#开发者工具-1\" class=\"headerlink\" title=\"开发者工具\"></a>开发者工具</h3><ul>\n<li>打开开发者工具：<code>Ctrl + Shift + I</code></li>\n<li>打开开发者工具的控制台面板：<code>Ctrl + Shift + J</code></li>\n<li>切换到下一个面板：<code>Ctrl + ]</code></li>\n<li>切换到上一个面板：<code>Ctrl + [</code></li>\n</ul>\n<hr>\n<h3 id=\"其他操作-1\"><a href=\"#其他操作-1\" class=\"headerlink\" title=\"其他操作\"></a>其他操作</h3><ul>\n<li>打开历史记录：<code>Ctrl + H</code></li>\n<li>打开书签栏：<code>Ctrl + Shift + B</code></li>\n<li>打开下载页面：<code>Ctrl + J</code></li>\n</ul>\n","text":"Chrome浏览器快捷键，就像一把魔法棒，让你在互联网世界中犹如骑着闪电！Ctrl+T开启新标签，Ctrl+W关闭标签，轻松驾驭浏览器舞台，尽享冒险乐趣！...","permalink":"/post/快捷键/Chrome 浏览器常用快捷键","photos":[],"count_time":{"symbolsCount":"1.2k","symbolsTime":"1 mins."},"categories":[{"name":"计算机","slug":"计算机","count":8,"path":"api/categories/计算机.json"},{"name":"快捷键","slug":"计算机/快捷键","count":1,"path":"api/categories/计算机/快捷键.json"}],"tags":[{"name":"笔记","slug":"笔记","count":10,"path":"api/tags/笔记.json"},{"name":"快捷键","slug":"快捷键","count":1,"path":"api/tags/快捷键.json"}],"toc":"<ol class=\"toc\"><li class=\"toc-item toc-level-1\"><a class=\"toc-link\" href=\"#Chrome-%E6%B5%8F%E8%A7%88%E5%99%A8%E5%B8%B8%E7%94%A8%E5%BF%AB%E6%8D%B7%E9%94%AE\"><span class=\"toc-text\">Chrome 浏览器常用快捷键</span></a><ol class=\"toc-child\"><li class=\"toc-item toc-level-2\"><a class=\"toc-link\" href=\"#Mac-%E4%B8%8A%E7%9A%84-Chrome-%E5%BF%AB%E6%8D%B7%E9%94%AE\"><span class=\"toc-text\">Mac 上的 Chrome 快捷键</span></a><ol class=\"toc-child\"><li class=\"toc-item toc-level-3\"><a class=\"toc-link\" href=\"#%E5%AF%BC%E8%88%AA\"><span class=\"toc-text\">导航</span></a></li><li class=\"toc-item toc-level-3\"><a class=\"toc-link\" href=\"#%E6%A0%87%E7%AD%BE%E9%A1%B5%E6%93%8D%E4%BD%9C\"><span class=\"toc-text\">标签页操作</span></a></li><li class=\"toc-item toc-level-3\"><a class=\"toc-link\" href=\"#%E6%9F%A5%E6%89%BE%E5%92%8C%E6%90%9C%E7%B4%A2\"><span class=\"toc-text\">查找和搜索</span></a></li><li class=\"toc-item toc-level-3\"><a class=\"toc-link\" href=\"#%E5%BC%80%E5%8F%91%E8%80%85%E5%B7%A5%E5%85%B7\"><span class=\"toc-text\">开发者工具</span></a></li><li class=\"toc-item toc-level-3\"><a class=\"toc-link\" href=\"#%E5%85%B6%E4%BB%96%E6%93%8D%E4%BD%9C\"><span class=\"toc-text\">其他操作</span></a></li></ol></li><li class=\"toc-item toc-level-2\"><a class=\"toc-link\" href=\"#Windows-%E4%B8%8A%E7%9A%84-Chrome-%E5%BF%AB%E6%8D%B7%E9%94%AE\"><span class=\"toc-text\">Windows 上的 Chrome 快捷键</span></a><ol class=\"toc-child\"><li class=\"toc-item toc-level-3\"><a class=\"toc-link\" href=\"#%E5%AF%BC%E8%88%AA-1\"><span class=\"toc-text\">导航</span></a></li><li class=\"toc-item toc-level-3\"><a class=\"toc-link\" href=\"#%E6%A0%87%E7%AD%BE%E9%A1%B5%E6%93%8D%E4%BD%9C-1\"><span class=\"toc-text\">标签页操作</span></a></li><li class=\"toc-item toc-level-3\"><a class=\"toc-link\" href=\"#%E6%9F%A5%E6%89%BE%E5%92%8C%E6%90%9C%E7%B4%A2-1\"><span class=\"toc-text\">查找和搜索</span></a></li><li class=\"toc-item toc-level-3\"><a class=\"toc-link\" href=\"#%E5%BC%80%E5%8F%91%E8%80%85%E5%B7%A5%E5%85%B7-1\"><span class=\"toc-text\">开发者工具</span></a></li><li class=\"toc-item toc-level-3\"><a class=\"toc-link\" href=\"#%E5%85%B6%E4%BB%96%E6%93%8D%E4%BD%9C-1\"><span class=\"toc-text\">其他操作</span></a></li></ol></li></ol></li></ol>","author":{"name":"Honman","slug":"blog-author","avatar":"/images/avatar.jpeg","link":"/","description":"这家伙很坏 什么都没留下","socials":{"github":"","twitter":"","stackoverflow":"","wechat":"","qq":"","weibo":"","zhihu":"","csdn":"","juejin":"","customs":{}}},"mapped":true,"hidden":false,"prev_post":{"title":"CET4笔记","uid":"377acfb2c7ae144090a23e072d60353b","slug":"English/CET4","date":"2022-05-25T09:59:41.000Z","updated":"2023-08-17T06:43:23.072Z","comments":true,"path":"api/articles/English/CET4.json","keywords":null,"cover":"/images/cover/5.jpg","text":"作文模板 Acknowledgements: ysat议论文（essay） 三个段落（ 10-11 句） 第一段（2-3 句） 前 1-2 句提出你的问题（你对...","permalink":"/post/English/CET4","photos":[],"count_time":{"symbolsCount":"11k","symbolsTime":"10 mins."},"categories":[{"name":"英语","slug":"英语","count":4,"path":"api/categories/英语.json"}],"tags":[{"name":"英语","slug":"英语","count":4,"path":"api/tags/英语.json"},{"name":"笔记","slug":"笔记","count":10,"path":"api/tags/笔记.json"}],"author":{"name":"Honman","slug":"blog-author","avatar":"/images/avatar.jpeg","link":"/","description":"这家伙很坏 什么都没留下","socials":{"github":"","twitter":"","stackoverflow":"","wechat":"","qq":"","weibo":"","zhihu":"","csdn":"","juejin":"","customs":{}}}},"next_post":{}}